{
  "sn87093220": {
    "title": "Aberdeen herald. [volume]",
    "earliest_date": "October 23, 1890",
    "raw_date": "1890-10-23",
    "state": "Washington"
  },
  "sn87093056": {
    "title": "Adams County news. [volume]",
    "earliest_date": "February 02, 1898",
    "raw_date": "1898-02-02",
    "state": "Washington"
  },
  "sn87093354": {
    "title": "Cayton&#39;s monthly. [volume]",
    "earliest_date": "February 01, 1921",
    "raw_date": "1921-02-01",
    "state": "Washington"
  },
  "sn87093353": {
    "title": "Cayton&#39;s weekly. [volume]",
    "earliest_date": "July 14, 1917",
    "raw_date": "1917-07-14",
    "state": "Washington"
  },
  "sn88085771": {
    "title": "The Co-operative news. [volume]",
    "earliest_date": "October 25, 1917",
    "raw_date": "1917-10-25",
    "state": "Washington"
  },
  "sn88085460": {
    "title": "The Colfax gazette. [volume]",
    "earliest_date": "January 05, 1900",
    "raw_date": "1900-01-05",
    "state": "Washington"
  },
  "sn87093028": {
    "title": "Columbia courier. [volume]",
    "earliest_date": "March 27, 1903",
    "raw_date": "1903-03-27",
    "state": "Washington"
  },
  "sn83025143": {
    "title": "The Columbian. [volume]",
    "earliest_date": "September 11, 1852",
    "raw_date": "1852-09-11",
    "state": "Washington"
  },
  "sn88085318": {
    "title": "The Colville examiner. [volume]",
    "earliest_date": "October 31, 1907",
    "raw_date": "1907-10-31",
    "state": "Washington"
  },
  "sn84025731": {
    "title": "The Commonwealth. [volume]",
    "earliest_date": "February 04, 1911",
    "raw_date": "1911-02-04",
    "state": "Washington"
  },
  "sn89079026": {
    "title": "Coulee City dispatch. [volume]",
    "earliest_date": "May 26, 1916",
    "raw_date": "1916-05-26",
    "state": "Washington"
  },
  "sn87093045": {
    "title": "Courier-herald. [volume]",
    "earliest_date": "November 05, 1949",
    "raw_date": "1949-11-05",
    "state": "Washington"
  },
  "sn83045610": {
    "title": "The daily intelligencer. [volume]",
    "earliest_date": "June 05, 1876",
    "raw_date": "1876-06-05",
    "state": "Washington"
  },
  "sn87093449": {
    "title": "The Daily Republican. [volume]",
    "earliest_date": "February 26, 1896",
    "raw_date": "1896-02-26",
    "state": "Washington"
  },
  "sn88085011": {
    "title": "The dawn. [volume]",
    "earliest_date": "August 04, 1894",
    "raw_date": "1894-08-04",
    "state": "Washington"
  },
  "2012252560": {
    "title": "The dawn. [volume]",
    "earliest_date": "January 19, 1895",
    "raw_date": "1895-01-19",
    "state": "Washington"
  },
  "sn88085012": {
    "title": "The Ellensburg dawn. [volume]",
    "earliest_date": "March 18, 1898",
    "raw_date": "1898-03-18",
    "state": "Washington"
  },
  "sn87093375": {
    "title": "The Enterprise. [volume]",
    "earliest_date": "October 08, 1926",
    "raw_date": "1926-10-08",
    "state": "Washington"
  },
  "sn88085421": {
    "title": "The Evening statesman. [volume]",
    "earliest_date": "May 26, 1903",
    "raw_date": "1903-05-26",
    "state": "Washington"
  },
  "sn88085722": {
    "title": "Fairhaven herald. [volume]",
    "earliest_date": "March 11, 1890",
    "raw_date": "1890-03-11",
    "state": "Washington"
  },
  "sn88085780": {
    "title": "Filipino forum. [volume]",
    "earliest_date": "October 15, 1928",
    "raw_date": "1928-10-15",
    "state": "Washington"
  },
  "sn88085617": {
    "title": "Industrial freedom. [volume]",
    "earliest_date": "May 07, 1898",
    "raw_date": "1898-05-07",
    "state": "Washington"
  },
  "sn88085189": {
    "title": "The islander. [volume]",
    "earliest_date": "March 06, 1891",
    "raw_date": "1891-03-06",
    "state": "Washington"
  },
  "sn87093007": {
    "title": "The Kennewick courier-reporter and the White Bluffs spokesman. [volume]",
    "earliest_date": "August 04, 1938",
    "raw_date": "1938-08-04",
    "state": "Washington"
  },
  "sn87093044": {
    "title": "The Kennewick courier-reporter. [volume]",
    "earliest_date": "January 05, 1939",
    "raw_date": "1939-01-05",
    "state": "Washington"
  },
  "sn87093042": {
    "title": "The Kennewick courier-reporter. [volume]",
    "earliest_date": "April 02, 1914",
    "raw_date": "1914-04-02",
    "state": "Washington"
  },
  "sn87093029": {
    "title": "The Kennewick courier. [volume]",
    "earliest_date": "April 28, 1905",
    "raw_date": "1905-04-28",
    "state": "Washington"
  },
  "sn88085620": {
    "title": "The labor journal. [volume]",
    "earliest_date": "January 07, 1909",
    "raw_date": "1909-01-07",
    "state": "Washington"
  },
  "sn87093039": {
    "title": "The Leavenworth echo. [volume]",
    "earliest_date": "January 29, 1904",
    "raw_date": "1904-01-29",
    "state": "Washington"
  },
  "sn88085445": {
    "title": "The Lynden tribune. [volume]",
    "earliest_date": "July 09, 1908",
    "raw_date": "1908-07-09",
    "state": "Washington"
  },
  "sn88085081": {
    "title": "The Mason County journal. [volume]",
    "earliest_date": "May 17, 1889",
    "raw_date": "1889-05-17",
    "state": "Washington"
  },
  "2019252177": {
    "title": "Monthly news of the Department of Washington. [volume]",
    "earliest_date": "March 01, 1943",
    "raw_date": "1943-03-01",
    "state": "Washington"
  },
  "sn88087034": {
    "title": "The Nespelem tribune. [volume]",
    "earliest_date": "August 08, 1934",
    "raw_date": "1934-08-08",
    "state": "Washington"
  },
  "sn87008085": {
    "title": "The Newport miner. [volume]",
    "earliest_date": "November 09, 1907",
    "raw_date": "1907-11-09",
    "state": "Washington"
  },
  "sn84022795": {
    "title": "The northern star. [volume]",
    "earliest_date": "January 15, 1876",
    "raw_date": "1876-01-15",
    "state": "Washington"
  },
  "sn88085204": {
    "title": "Northwest enterprise. [volume]",
    "earliest_date": "March 25, 1882",
    "raw_date": "1882-03-25",
    "state": "Washington"
  },
  "sn87093377": {
    "title": "The Northwest enterprise. [volume]",
    "earliest_date": "January 01, 1931",
    "raw_date": "1931-01-01",
    "state": "Washington"
  },
  "sn86071999": {
    "title": "The Northwest times. [volume]",
    "earliest_date": "January 01, 1947",
    "raw_date": "1947-01-01",
    "state": "Washington"
  },
  "sn88085770": {
    "title": "The Northwest worker. [volume]",
    "earliest_date": "July 01, 1915",
    "raw_date": "1915-07-01",
    "state": "Washington"
  },
  "sn88085350": {
    "title": "Olympia tribune. [volume]",
    "earliest_date": "October 09, 1891",
    "raw_date": "1891-10-09",
    "state": "Washington"
  },
  "sn88085101": {
    "title": "The Oroville weekly gazette. [volume]",
    "earliest_date": "January 01, 1909",
    "raw_date": "1909-01-01",
    "state": "Washington"
  },
  "sn83025141": {
    "title": "Pioneer and Democrat. [volume]",
    "earliest_date": "February 04, 1854",
    "raw_date": "1854-02-04",
    "state": "Washington"
  },
  "sn96061106": {
    "title": "Puget Sound Argus. [volume]",
    "earliest_date": "May 26, 1882",
    "raw_date": "1882-05-26",
    "state": "Washington"
  },
  "sn84022793": {
    "title": "Puget Sound dispatch. [volume]",
    "earliest_date": "December 04, 1871",
    "raw_date": "1871-12-04",
    "state": "Washington"
  },
  "sn88085145": {
    "title": "Puget Sound herald. [volume]",
    "earliest_date": "March 12, 1858",
    "raw_date": "1858-03-12",
    "state": "Washington"
  },
  "sn96061109": {
    "title": "Puget Sound weekly Argus. [volume]",
    "earliest_date": "January 26, 1888",
    "raw_date": "1888-01-26",
    "state": "Washington"
  },
  "sn96061107": {
    "title": "Puget Sound weekly Argus. [volume]",
    "earliest_date": "May 31, 1883",
    "raw_date": "1883-05-31",
    "state": "Washington"
  },
  "sn84022761": {
    "title": "Puget Sound weekly Argus. [volume]",
    "earliest_date": "January 01, 1876",
    "raw_date": "1876-01-01",
    "state": "Washington"
  },
  "sn88085488": {
    "title": "Pullman herald. [volume]",
    "earliest_date": "November 03, 1888",
    "raw_date": "1888-11-03",
    "state": "Washington"
  },
  "2007252175": {
    "title": "The ranch. [volume]",
    "earliest_date": "January 20, 1894",
    "raw_date": "1894-01-20",
    "state": "Washington"
  },
  "sn98047754": {
    "title": "The ranch. [volume]",
    "earliest_date": "September 01, 1902",
    "raw_date": "1902-09-01",
    "state": "Washington"
  },
  "2007252185": {
    "title": "Ranche and range. [volume]",
    "earliest_date": "April 08, 1897",
    "raw_date": "1897-04-08",
    "state": "Washington"
  },
  "2012252554": {
    "title": "The reformer&#39;s dawn. [volume]",
    "earliest_date": "November 01, 1893",
    "raw_date": "1893-11-01",
    "state": "Washington"
  },
  "sn87093448": {
    "title": "The Republican. [volume]",
    "earliest_date": "August 22, 1896",
    "raw_date": "1896-08-22",
    "state": "Washington"
  },
  "sn88085190": {
    "title": "The San Juan islander. [volume]",
    "earliest_date": "February 24, 1898",
    "raw_date": "1898-02-24",
    "state": "Washington"
  },
  "sn87093436": {
    "title": "Scandinavian American. [volume]",
    "earliest_date": "January 01, 1945",
    "raw_date": "1945-01-01",
    "state": "Washington"
  },
  "sn83045611": {
    "title": "Seattle daily post-intelligencer. [volume]",
    "earliest_date": "April 05, 1882",
    "raw_date": "1882-04-05",
    "state": "Washington"
  },
  "sn87093376": {
    "title": "The Seattle enterprise. [volume]",
    "earliest_date": "May 14, 1921",
    "raw_date": "1921-05-14",
    "state": "Washington"
  },
  "sn83045604": {
    "title": "The Seattle post-intelligencer. [volume]",
    "earliest_date": "May 11, 1888",
    "raw_date": "1888-05-11",
    "state": "Washington"
  },
  "sn84025811": {
    "title": "The Seattle Republican. [volume]",
    "earliest_date": "January 19, 1900",
    "raw_date": "1900-01-19",
    "state": "Washington"
  },
  "sn87093407": {
    "title": "The Seattle star. [volume]",
    "earliest_date": "February 27, 1899",
    "raw_date": "1899-02-27",
    "state": "Washington"
  },
  "sn88087163": {
    "title": "Southwest Washington labor press. [volume]",
    "earliest_date": "November 24, 1922",
    "raw_date": "1922-11-24",
    "state": "Washington"
  },
  "sn86072021": {
    "title": "Spokane Falls review. [volume]",
    "earliest_date": "May 19, 1883",
    "raw_date": "1883-05-19",
    "state": "Washington"
  },
  "sn88085947": {
    "title": "The Spokane press. [volume]",
    "earliest_date": "November 07, 1902",
    "raw_date": "1902-11-07",
    "state": "Washington"
  },
  "sn88087129": {
    "title": "The Spokane woman. [volume]",
    "earliest_date": "September 23, 1926",
    "raw_date": "1926-09-23",
    "state": "Washington"
  },
  "sn88085187": {
    "title": "The Tacoma times. [volume]",
    "earliest_date": "December 21, 1903",
    "raw_date": "1903-12-21",
    "state": "Washington"
  },
  "sn87093109": {
    "title": "The Vancouver independent.",
    "earliest_date": "September 04, 1875",
    "raw_date": "1875-09-04",
    "state": "Washington"
  },
  "sn87093323": {
    "title": "Vashon Island news-record. [volume]",
    "earliest_date": "December 18, 1919",
    "raw_date": "1919-12-18",
    "state": "Washington"
  },
  "sn92038389": {
    "title": "Vashon Island news. [volume]",
    "earliest_date": "May 24, 1907",
    "raw_date": "1907-05-24",
    "state": "Washington"
  },
  "sn92038390": {
    "title": "The Vashon Island record. [volume]",
    "earliest_date": "October 26, 1916",
    "raw_date": "1916-10-26",
    "state": "Washington"
  },
  "2019252178": {
    "title": "Veterans news. [volume]",
    "earliest_date": "July 01, 1946",
    "raw_date": "1946-07-01",
    "state": "Washington"
  },
  "2019252176": {
    "title": "The veterans&#39; review. [volume]",
    "earliest_date": "January 01, 1936",
    "raw_date": "1936-01-01",
    "state": "Washington"
  },
  "sn88085651": {
    "title": "Victory worker. [volume]",
    "earliest_date": "June 01, 1942",
    "raw_date": "1942-06-01",
    "state": "Washington"
  },
  "sn88085733": {
    "title": "Voice of action. [volume]",
    "earliest_date": "April 24, 1934",
    "raw_date": "1934-04-24",
    "state": "Washington"
  },
  "sn86072040": {
    "title": "Walla Walla statesman. [volume]",
    "earliest_date": "September 02, 1864",
    "raw_date": "1864-09-02",
    "state": "Washington"
  },
  "sn98047755": {
    "title": "Washington farmer. [volume]",
    "earliest_date": "June 15, 1914",
    "raw_date": "1914-06-15",
    "state": "Washington"
  },
  "sn83025142": {
    "title": "Washington pioneer. [volume]",
    "earliest_date": "December 03, 1853",
    "raw_date": "1853-12-03",
    "state": "Washington"
  },
  "sn88085769": {
    "title": "The Washington socialist. [volume]",
    "earliest_date": "April 16, 1914",
    "raw_date": "1914-04-16",
    "state": "Washington"
  },
  "sn84022770": {
    "title": "Washington standard. [volume]",
    "earliest_date": "November 17, 1860",
    "raw_date": "1860-11-17",
    "state": "Washington"
  },
  "sn87093057": {
    "title": "Washington State journal and Adams County news. [volume]",
    "earliest_date": "October 24, 1906",
    "raw_date": "1906-10-24",
    "state": "Washington"
  },
  "sn87093055": {
    "title": "Washington State journal. [volume]",
    "earliest_date": "November 06, 1907",
    "raw_date": "1907-11-06",
    "state": "Washington"
  },
  "sn84022799": {
    "title": "Washington statesman. [volume]",
    "earliest_date": "December 13, 1861",
    "raw_date": "1861-12-13",
    "state": "Washington"
  },
  "sn87093274": {
    "title": "The weekly Argus. [volume]",
    "earliest_date": "December 29, 1870",
    "raw_date": "1870-12-29",
    "state": "Washington"
  },
  "2012252559": {
    "title": "The weekly dawn. [volume]",
    "earliest_date": "August 11, 1894",
    "raw_date": "1894-08-11",
    "state": "Washington"
  },
  "sn96061108": {
    "title": "Weekly Puget Sound Argus. [volume]",
    "earliest_date": "December 24, 1885",
    "raw_date": "1885-12-24",
    "state": "Washington"
  },
  "sn86072041": {
    "title": "The Wenatchee daily world. [volume]",
    "earliest_date": "July 03, 1905",
    "raw_date": "1905-07-03",
    "state": "Washington"
  },
  "sn87093008": {
    "title": "White Bluffs spokesman. [volume]",
    "earliest_date": "December 10, 1915",
    "raw_date": "1915-12-10",
    "state": "Washington"
  },
  "sn84025812": {
    "title": "The world. [volume]",
    "earliest_date": "January 04, 1899",
    "raw_date": "1899-01-04",
    "state": "Washington"
  },
  "sn88085523": {
    "title": "The Yakima herald. [volume]",
    "earliest_date": "February 02, 1889",
    "raw_date": "1889-02-02",
    "state": "Washington"
  },
  "sn93052980": {
    "title": "Amador ledger.",
    "earliest_date": "January 05, 1900",
    "raw_date": "1900-01-05",
    "state": "California"
  },
  "sn93051029": {
    "title": "Amador weekly ledger.",
    "earliest_date": "October 24, 1857",
    "raw_date": "1857-10-24",
    "state": "California"
  },
  "sn93052998": {
    "title": "Butte record.",
    "earliest_date": "November 12, 1853",
    "raw_date": "1853-11-12",
    "state": "California"
  },
  "sn84026973": {
    "title": "Calaveras chronicle. [volume]",
    "earliest_date": "October 18, 1851",
    "raw_date": "1851-10-18",
    "state": "California"
  },
  "sn82015732": {
    "title": "The Call-chronicle-examiner. [volume]",
    "earliest_date": "April 19, 1906",
    "raw_date": "1906-04-19",
    "state": "California"
  },
  "sn93052786": {
    "title": "El clamor pu\u0301blico. [volume]",
    "earliest_date": "June 19, 1855",
    "raw_date": "1855-06-19",
    "state": "California"
  },
  "sn82014554": {
    "title": "Columbia gazette and the southern mines advertiser. [volume]",
    "earliest_date": "May 27, 1858",
    "raw_date": "1858-05-27",
    "state": "California"
  },
  "sn84038765": {
    "title": "Columbia gazette. [volume]",
    "earliest_date": "November 12, 1853",
    "raw_date": "1853-11-12",
    "state": "California"
  },
  "sn92068455": {
    "title": "Columbia weekly news.",
    "earliest_date": "August 26, 1858",
    "raw_date": "1858-08-26",
    "state": "California"
  },
  "sn84025126": {
    "title": "La cro\u0301nica. [volume]",
    "earliest_date": "May 04, 1872",
    "raw_date": "1872-05-04",
    "state": "California"
  },
  "sn87056985": {
    "title": "La cro\u0301nica.",
    "earliest_date": "April 25, 1914",
    "raw_date": "1914-04-25",
    "state": "California"
  },
  "sn86058107": {
    "title": "The daily Butte record. [volume]",
    "earliest_date": "February 01, 1858",
    "raw_date": "1858-02-01",
    "state": "California"
  },
  "sn85042459": {
    "title": "Daily Los Angeles herald. [microfilm reel]",
    "earliest_date": "January 03, 1878",
    "raw_date": "1878-01-03",
    "state": "California"
  },
  "sn84038814": {
    "title": "Daily national Democrat. [volume]",
    "earliest_date": "August 13, 1858",
    "raw_date": "1858-08-13",
    "state": "California"
  },
  "sn83027101": {
    "title": "The elevator. [volume]",
    "earliest_date": "September 08, 1888",
    "raw_date": "1888-09-08",
    "state": "California"
  },
  "sn82014869": {
    "title": "The Empire County argus. [volume]",
    "earliest_date": "November 19, 1853",
    "raw_date": "1853-11-19",
    "state": "California"
  },
  "sn93052972": {
    "title": "The Georgetown news.",
    "earliest_date": "June 21, 1855",
    "raw_date": "1855-06-21",
    "state": "California"
  },
  "sn93052971": {
    "title": "Georgetown weekly news.",
    "earliest_date": "October 19, 1854",
    "raw_date": "1854-10-19",
    "state": "California"
  },
  "sn84026882": {
    "title": "Grass Valley telegraph. [volume]",
    "earliest_date": "October 06, 1853",
    "raw_date": "1853-10-06",
    "state": "California"
  },
  "sn85042461": {
    "title": "The herald. [microfilm reel]",
    "earliest_date": "January 16, 1893",
    "raw_date": "1893-01-16",
    "state": "California"
  },
  "sn87021178": {
    "title": "Hispano Ame\u0301rica. [volume]",
    "earliest_date": "April 15, 1917",
    "raw_date": "1917-04-15",
    "state": "California"
  },
  "sn93051083": {
    "title": "The hydraulic press.",
    "earliest_date": "August 21, 1858",
    "raw_date": "1858-08-21",
    "state": "California"
  },
  "sn92070142": {
    "title": "Imperial press and farmer.",
    "earliest_date": "November 02, 1901",
    "raw_date": "1901-11-02",
    "state": "California"
  },
  "sn92070143": {
    "title": "The Imperial press.",
    "earliest_date": "April 04, 1903",
    "raw_date": "1903-04-04",
    "state": "California"
  },
  "sn98061398": {
    "title": "Imperial press.",
    "earliest_date": "April 20, 1901",
    "raw_date": "1901-04-20",
    "state": "California"
  },
  "sn92070144": {
    "title": "Imperial Valley press and the Imperial press.",
    "earliest_date": "March 24, 1906",
    "raw_date": "1906-03-24",
    "state": "California"
  },
  "sn92070146": {
    "title": "Imperial Valley press.",
    "earliest_date": "July 23, 1907",
    "raw_date": "1907-07-23",
    "state": "California"
  },
  "sn85066408": {
    "title": "L&#39;Italia. [volume]",
    "earliest_date": "January 25, 1897",
    "raw_date": "1897-01-25",
    "state": "California"
  },
  "sn93062881": {
    "title": "The Llano colonist. [volume]",
    "earliest_date": "March 11, 1922",
    "raw_date": "1922-03-11",
    "state": "California"
  },
  "sn85042460": {
    "title": "Los Angeles daily herald. [microfilm reel]",
    "earliest_date": "October 07, 1884",
    "raw_date": "1884-10-07",
    "state": "California"
  },
  "sn84038806": {
    "title": "Los Angeles daily herald. [volume]",
    "earliest_date": "October 02, 1873",
    "raw_date": "1873-10-02",
    "state": "California"
  },
  "sn85042462": {
    "title": "Los Angeles herald. [microfilm reel]",
    "earliest_date": "January 01, 1905",
    "raw_date": "1905-01-01",
    "state": "California"
  },
  "sn84025968": {
    "title": "Los Angeles herald. [volume]",
    "earliest_date": "March 23, 1890",
    "raw_date": "1890-03-23",
    "state": "California"
  },
  "sn84026978": {
    "title": "Mariposa Democrat. [volume]",
    "earliest_date": "April 01, 1857",
    "raw_date": "1857-04-01",
    "state": "California"
  },
  "sn83027100": {
    "title": "Mirror of the times. [volume]",
    "earliest_date": "December 12, 1857",
    "raw_date": "1857-12-12",
    "state": "California"
  },
  "sn94052989": {
    "title": "The morning call. [volume]",
    "earliest_date": "April 01, 1890",
    "raw_date": "1890-04-01",
    "state": "California"
  },
  "sn82014487": {
    "title": "The mountain Democrat. [volume]",
    "earliest_date": "January 03, 1863",
    "raw_date": "1863-01-03",
    "state": "California"
  },
  "sn82014488": {
    "title": "Mountain Democrat. [volume]",
    "earliest_date": "March 21, 1857",
    "raw_date": "1857-03-21",
    "state": "California"
  },
  "sn84026881": {
    "title": "The Nevada Democrat. [volume]",
    "earliest_date": "August 20, 1856",
    "raw_date": "1856-08-20",
    "state": "California"
  },
  "sn84026884": {
    "title": "The Nevada journal. [volume]",
    "earliest_date": "April 19, 1851",
    "raw_date": "1851-04-19",
    "state": "California"
  },
  "sn86058101": {
    "title": "Nevada national. [volume]",
    "earliest_date": "January 08, 1859",
    "raw_date": "1859-01-08",
    "state": "California"
  },
  "sn84025837": {
    "title": "Oakland sunshine. [volume]",
    "earliest_date": "March 20, 1915",
    "raw_date": "1915-03-20",
    "state": "California"
  },
  "sn81004351": {
    "title": "La opinio\u0301n. [volume]",
    "earliest_date": "September 18, 1926",
    "raw_date": "1926-09-18",
    "state": "California"
  },
  "sn86058106": {
    "title": "Oroville daily Butte record. [volume]",
    "earliest_date": "July 14, 1856",
    "raw_date": "1856-07-14",
    "state": "California"
  },
  "sn83027099": {
    "title": "The Pacific appeal. [volume]",
    "earliest_date": "April 24, 1875",
    "raw_date": "1875-04-24",
    "state": "California"
  },
  "sn82014998": {
    "title": "The Placer herald. [volume]",
    "earliest_date": "September 15, 1855",
    "raw_date": "1855-09-15",
    "state": "California"
  },
  "sn83045394": {
    "title": "La prensa. [volume]",
    "earliest_date": "December 08, 1917",
    "raw_date": "1917-12-08",
    "state": "California"
  },
  "sn82015104": {
    "title": "The record-union. [volume]",
    "earliest_date": "January 10, 1891",
    "raw_date": "1891-01-10",
    "state": "California"
  },
  "sn82014381": {
    "title": "Sacramento daily record-union. [volume]",
    "earliest_date": "January 01, 1880",
    "raw_date": "1880-01-01",
    "state": "California"
  },
  "sn85025090": {
    "title": "San Andreas independent. [volume]",
    "earliest_date": "September 24, 1856",
    "raw_date": "1856-09-24",
    "state": "California"
  },
  "sn86064451": {
    "title": "The San Francisco call and post. [volume]",
    "earliest_date": "December 09, 1913",
    "raw_date": "1913-12-09",
    "state": "California"
  },
  "sn85066387": {
    "title": "The San Francisco call. [volume]",
    "earliest_date": "March 05, 1895",
    "raw_date": "1895-03-05",
    "state": "California"
  },
  "sn84025838": {
    "title": "San Francisco vindicator. [volume]",
    "earliest_date": "May 02, 1887",
    "raw_date": "1887-05-02",
    "state": "California"
  },
  "sn87067106": {
    "title": "The semi-weekly mountain Democrat.",
    "earliest_date": "August 22, 1860",
    "raw_date": "1860-08-22",
    "state": "California"
  },
  "sn82015099": {
    "title": "The Shasta courier. [volume]",
    "earliest_date": "March 12, 1853",
    "raw_date": "1853-03-12",
    "state": "California"
  },
  "sn87067105": {
    "title": "The Sierra citizen.",
    "earliest_date": "March 19, 1859",
    "raw_date": "1859-03-19",
    "state": "California"
  },
  "sn86058097": {
    "title": "The Sierra citizen. [volume]",
    "earliest_date": "February 11, 1854",
    "raw_date": "1854-02-11",
    "state": "California"
  },
  "sn86064439": {
    "title": "Su\u0308d California Deutsche zeitung. [volume]",
    "earliest_date": "April 23, 1887",
    "raw_date": "1887-04-23",
    "state": "California"
  },
  "sn93053243": {
    "title": "The Trinity journal. [volume]",
    "earliest_date": "January 26, 1856",
    "raw_date": "1856-01-26",
    "state": "California"
  },
  "sn85025203": {
    "title": "The Trinity times. [volume]",
    "earliest_date": "December 23, 1854",
    "raw_date": "1854-12-23",
    "state": "California"
  },
  "sn85025134": {
    "title": "The union Democrat. [volume]",
    "earliest_date": "October 13, 1855",
    "raw_date": "1855-10-13",
    "state": "California"
  },
  "sn93051027": {
    "title": "Volcano weekly ledger.",
    "earliest_date": "October 27, 1855",
    "raw_date": "1855-10-27",
    "state": "California"
  },
  "sn86058108": {
    "title": "The weekly Butte record. [volume]",
    "earliest_date": "September 18, 1858",
    "raw_date": "1858-09-18",
    "state": "California"
  },
  "sn84038763": {
    "title": "The weekly Butte record. [volume]",
    "earliest_date": "March 24, 1866",
    "raw_date": "1866-03-24",
    "state": "California"
  },
  "sn93052977": {
    "title": "Weekly Calaveras chronicle.",
    "earliest_date": "March 10, 1866",
    "raw_date": "1866-03-10",
    "state": "California"
  },
  "sn84038768": {
    "title": "The weekly Columbian. [volume]",
    "earliest_date": "June 28, 1856",
    "raw_date": "1856-06-28",
    "state": "California"
  },
  "sn93051028": {
    "title": "The weekly ledger.",
    "earliest_date": "April 18, 1857",
    "raw_date": "1857-04-18",
    "state": "California"
  },
  "sn82014489": {
    "title": "The weekly mountain Democrat. [volume]",
    "earliest_date": "January 05, 1861",
    "raw_date": "1861-01-05",
    "state": "California"
  },
  "sn93052117": {
    "title": "The weekly Placer herald.",
    "earliest_date": "September 11, 1852",
    "raw_date": "1852-09-11",
    "state": "California"
  },
  "sn85025132": {
    "title": "The weekly Shasta courier. [volume]",
    "earliest_date": "December 21, 1872",
    "raw_date": "1872-12-21",
    "state": "California"
  },
  "sn84038779": {
    "title": "The weekly Sierra citizen. [volume]",
    "earliest_date": "June 28, 1856",
    "raw_date": "1856-06-28",
    "state": "California"
  },
  "sn85025202": {
    "title": "Weekly Trinity journal. [volume]",
    "earliest_date": "February 14, 1857",
    "raw_date": "1857-02-14",
    "state": "California"
  },
  "sn86076422": {
    "title": "The weekly union record. [volume]",
    "earliest_date": "January 23, 1864",
    "raw_date": "1864-01-23",
    "state": "California"
  },
  "sn84025815": {
    "title": "The Western outlook. [volume]",
    "earliest_date": "January 27, 1900",
    "raw_date": "1900-01-27",
    "state": "California"
  },
  "sn85042252": {
    "title": "Black Republican and office-holder&#39;s journal. [volume]",
    "earliest_date": "August 10, 1865",
    "raw_date": "1865-08-10",
    "state": "New York"
  },
  "sn84020097": {
    "title": "The daily worker. [volume]",
    "earliest_date": "January 13, 1924",
    "raw_date": "1924-01-13",
    "state": "Illinois"
  },
  "sn83030193": {
    "title": "The evening world. [volume]",
    "earliest_date": "October 10, 1887",
    "raw_date": "1887-10-10",
    "state": "New York"
  },
  "sn83027103": {
    "title": "The freeman. [volume]",
    "earliest_date": "November 22, 1884",
    "raw_date": "1884-11-22",
    "state": "New York"
  },
  "sn83030483": {
    "title": "Gazette of the United-States. [volume]",
    "earliest_date": "April 15, 1789",
    "raw_date": "1789-04-15",
    "state": "New York"
  },
  "sn83030311": {
    "title": "The herald. [volume]",
    "earliest_date": "January 01, 1836",
    "raw_date": "1836-01-01",
    "state": "New York"
  },
  "sn83045837": {
    "title": "Der Morgen zshurnal = The Jewish morning journal. [volume]",
    "earliest_date": "January 02, 1910",
    "raw_date": "1910-01-02",
    "state": "New York"
  },
  "sn83045838": {
    "title": "Der Morgen zshurnal, yidishes t\u0323ageblat\u0323 = The Jewish morning journal and the Jewish daily news. [volume]",
    "earliest_date": "January 01, 1929",
    "raw_date": "1929-01-01",
    "state": "New York"
  },
  "sn83030312": {
    "title": "Morning herald. [volume]",
    "earliest_date": "May 22, 1837",
    "raw_date": "1837-05-22",
    "state": "New York"
  },
  "sn83030005": {
    "title": "The New York age. [volume]",
    "earliest_date": "October 15, 1887",
    "raw_date": "1887-10-15",
    "state": "New York"
  },
  "sn85026214": {
    "title": "New York dispatch. [volume]",
    "earliest_date": "July 05, 1863",
    "raw_date": "1863-07-05",
    "state": "New York"
  },
  "sn83027102": {
    "title": "The New York freeman. [volume]",
    "earliest_date": "December 13, 1884",
    "raw_date": "1884-12-13",
    "state": "New York"
  },
  "sn83027106": {
    "title": "The New York globe. [volume]",
    "earliest_date": "January 06, 1883",
    "raw_date": "1883-01-06",
    "state": "New York"
  },
  "sn83030313": {
    "title": "The New York herald. [volume]",
    "earliest_date": "January 01, 1842",
    "raw_date": "1842-01-01",
    "state": "New York"
  },
  "sn83045774": {
    "title": "The New York herald. [volume]",
    "earliest_date": "October 01, 1920",
    "raw_date": "1920-10-01",
    "state": "New York"
  },
  "sn83030213": {
    "title": "New-York daily tribune. [volume]",
    "earliest_date": "April 22, 1842",
    "raw_date": "1842-04-22",
    "state": "New York"
  },
  "sn83030364": {
    "title": "New-York dispatch. [volume]",
    "earliest_date": "June 11, 1854",
    "raw_date": "1854-06-11",
    "state": "New York"
  },
  "sn83030212": {
    "title": "New-York tribune. [volume]",
    "earliest_date": "April 10, 1841",
    "raw_date": "1841-04-10",
    "state": "New York"
  },
  "sn83030214": {
    "title": "New-York tribune. [volume]",
    "earliest_date": "April 10, 1866",
    "raw_date": "1866-04-10",
    "state": "New York"
  },
  "sn83027104": {
    "title": "The northern star and freemen&#39;s advocate.",
    "earliest_date": "February 03, 1842",
    "raw_date": "1842-02-03",
    "state": "New York"
  },
  "sn83035526": {
    "title": "Radnic\u030cka borba = Workers&#39; struggle. [volume]",
    "earliest_date": "January 16, 1941",
    "raw_date": "1941-01-16",
    "state": "New York"
  },
  "sn84025829": {
    "title": "The ram&#39;s horn. [volume]",
    "earliest_date": "November 05, 1847",
    "raw_date": "1847-11-05",
    "state": "New York"
  },
  "sn86071738": {
    "title": "Rassvet = Dawn.",
    "earliest_date": "May 01, 1925",
    "raw_date": "1925-05-01",
    "state": "New York"
  },
  "sn83027094": {
    "title": "The rights of all. [volume]",
    "earliest_date": "May 29, 1829",
    "raw_date": "1829-05-29",
    "state": "New York"
  },
  "sn83030430": {
    "title": "The Sun and New York press. [volume]",
    "earliest_date": "July 03, 1916",
    "raw_date": "1916-07-03",
    "state": "New York"
  },
  "sn83030273": {
    "title": "The Sun and the New York herald. [volume]",
    "earliest_date": "February 01, 1920",
    "raw_date": "1920-02-01",
    "state": "New York"
  },
  "sn83030272": {
    "title": "The sun. [volume]",
    "earliest_date": "October 01, 1859",
    "raw_date": "1859-10-01",
    "state": "New York"
  },
  "sn83030431": {
    "title": "The sun. [volume]",
    "earliest_date": "July 31, 1916",
    "raw_date": "1916-07-31",
    "state": "New York"
  },
  "sn85026213": {
    "title": "Sunday dispatch. [volume]",
    "earliest_date": "November 17, 1861",
    "raw_date": "1861-11-17",
    "state": "New York"
  },
  "sn83030362": {
    "title": "Sunday dispatch. [volume]",
    "earliest_date": "December 07, 1845",
    "raw_date": "1845-12-07",
    "state": "New York"
  },
  "sn83045861": {
    "title": "Der Tog = The Day. [volume]",
    "earliest_date": "September 01, 1940",
    "raw_date": "1940-09-01",
    "state": "New York"
  },
  "sn88078683": {
    "title": "The toiler. [volume]",
    "earliest_date": "January 07, 1920",
    "raw_date": "1920-01-07",
    "state": "New York"
  },
  "sn83030179": {
    "title": "The weekly Anglo-African. [volume]",
    "earliest_date": "July 23, 1859",
    "raw_date": "1859-07-23",
    "state": "New York"
  },
  "sn99066040": {
    "title": "The weekly sun.",
    "earliest_date": "July 13, 1861",
    "raw_date": "1861-07-13",
    "state": "New York"
  },
  "sn90065027": {
    "title": "Workmen&#39;s advocate.",
    "earliest_date": "September 08, 1883",
    "raw_date": "1883-09-08",
    "state": "New York"
  },
  "sn86063496": {
    "title": "Yidishes t\u0323ageblat\u0323t\u0323 = The Jewish daily news. [volume]",
    "earliest_date": "January 02, 1916",
    "raw_date": "1916-01-02",
    "state": "New York"
  },
  "sn83045003": {
    "title": "Abendblatt der Illinois Staats-zeitung. [volume]",
    "earliest_date": "March 27, 1893",
    "raw_date": "1893-03-27",
    "state": "Illinois"
  },
  "sn83045004": {
    "title": "Abendblatt. [volume]",
    "earliest_date": "October 24, 1894",
    "raw_date": "1894-10-24",
    "state": "Illinois"
  },
  "sn83045274": {
    "title": "Ameryka echo. [volume]",
    "earliest_date": "December 06, 1902",
    "raw_date": "1902-12-06",
    "state": "Illinois"
  },
  "sn83016810": {
    "title": "The Appeal. [volume]",
    "earliest_date": "February 23, 1889",
    "raw_date": "1889-02-23",
    "state": "Illinois"
  },
  "sn92053944": {
    "title": "The Argus.",
    "earliest_date": "October 01, 1885",
    "raw_date": "1885-10-01",
    "state": "Illinois"
  },
  "sn90050009": {
    "title": "The Arkansaw traveler.",
    "earliest_date": "June 04, 1882",
    "raw_date": "1882-06-04",
    "state": "Illinois"
  },
  "sn84024055": {
    "title": "The broad ax. [volume]",
    "earliest_date": "August 31, 1895",
    "raw_date": "1895-08-31",
    "state": "Illinois"
  },
  "sn85033413": {
    "title": "The Cairo bulletin. [volume]",
    "earliest_date": "November 15, 1872",
    "raw_date": "1872-11-15",
    "state": "Illinois"
  },
  "sn93055779": {
    "title": "The Cairo bulletin.",
    "earliest_date": "January 01, 1904",
    "raw_date": "1904-01-01",
    "state": "Illinois"
  },
  "sn88074142": {
    "title": "The Cairo daily bulletin.",
    "earliest_date": "March 29, 1870",
    "raw_date": "1870-03-29",
    "state": "Illinois"
  },
  "sn88074143": {
    "title": "The Cairo evening bulletin.",
    "earliest_date": "December 21, 1868",
    "raw_date": "1868-12-21",
    "state": "Illinois"
  },
  "sn84038364": {
    "title": "Cairo evening times. [volume]",
    "earliest_date": "September 01, 1865",
    "raw_date": "1865-09-01",
    "state": "Illinois"
  },
  "sn84031489": {
    "title": "Chicago daily press and tribune. [volume]",
    "earliest_date": "January 01, 1859",
    "raw_date": "1859-01-01",
    "state": "Illinois"
  },
  "sn84031492": {
    "title": "Chicago daily tribune. [volume]",
    "earliest_date": "October 09, 1872",
    "raw_date": "1872-10-09",
    "state": "Illinois"
  },
  "sn84031490": {
    "title": "Chicago daily tribune. [volume]",
    "earliest_date": "October 25, 1860",
    "raw_date": "1860-10-25",
    "state": "Illinois"
  },
  "sn84025828": {
    "title": "Chicago eagle. [volume]",
    "earliest_date": "October 05, 1889",
    "raw_date": "1889-10-05",
    "state": "Illinois"
  },
  "sn90053126": {
    "title": "The Chicago Illinois idea.",
    "earliest_date": "October 28, 1916",
    "raw_date": "1916-10-28",
    "state": "Illinois"
  },
  "sn91055768": {
    "title": "The Chicago reflector.",
    "earliest_date": "October 16, 1897",
    "raw_date": "1897-10-16",
    "state": "Illinois"
  },
  "sn87062321": {
    "title": "The Chicago star.",
    "earliest_date": "July 06, 1946",
    "raw_date": "1946-07-06",
    "state": "Illinois"
  },
  "sn82014064": {
    "title": "Chicago tribune. [volume]",
    "earliest_date": "August 21, 1864",
    "raw_date": "1864-08-21",
    "state": "Illinois"
  },
  "sn86056950": {
    "title": "The Chicago whip.",
    "earliest_date": "June 24, 1919",
    "raw_date": "1919-06-24",
    "state": "Illinois"
  },
  "sn91055455": {
    "title": "Chicago world.",
    "earliest_date": "June 23, 1934",
    "raw_date": "1934-06-23",
    "state": "Illinois"
  },
  "sn84025819": {
    "title": "The Chicago world. [volume]",
    "earliest_date": "January 27, 1900",
    "raw_date": "1900-01-27",
    "state": "Illinois"
  },
  "sn84024048": {
    "title": "The conservator. [volume]",
    "earliest_date": "November 18, 1882",
    "raw_date": "1882-11-18",
    "state": "Illinois"
  },
  "sn92053942": {
    "title": "The daily Argus.",
    "earliest_date": "December 08, 1873",
    "raw_date": "1873-12-08",
    "state": "Illinois"
  },
  "sn87082573": {
    "title": "The daily Cairo bulletin.",
    "earliest_date": "May 02, 1878",
    "raw_date": "1878-05-02",
    "state": "Illinois"
  },
  "sn83045487": {
    "title": "The day book. [volume]",
    "earliest_date": "November 01, 1911",
    "raw_date": "1911-11-01",
    "state": "Illinois"
  },
  "sn83045087": {
    "title": "Draugas. [volume]",
    "earliest_date": "January 02, 1917",
    "raw_date": "1917-01-02",
    "state": "Illinois"
  },
  "sn83045747": {
    "title": "Dziennik Chicagoski. [volume]",
    "earliest_date": "December 15, 1890",
    "raw_date": "1890-12-15",
    "state": "Illinois"
  },
  "sn83045097": {
    "title": "Dziennik narodowy. [volume]",
    "earliest_date": "May 25, 1900",
    "raw_date": "1900-05-25",
    "state": "Illinois"
  },
  "sn82015374": {
    "title": "Edwardsville spectator. [volume]",
    "earliest_date": "May 29, 1819",
    "raw_date": "1819-05-29",
    "state": "Illinois"
  },
  "sn84038628": {
    "title": "The evening Argus. [volume]",
    "earliest_date": "January 02, 1862",
    "raw_date": "1862-01-02",
    "state": "Illinois"
  },
  "sn86086415": {
    "title": "The forum. [volume]",
    "earliest_date": "February 03, 1906",
    "raw_date": "1906-02-03",
    "state": "Illinois"
  },
  "sn92053241": {
    "title": "Free trader-journal and Ottawa fair dealer.",
    "earliest_date": "March 08, 1920",
    "raw_date": "1920-03-08",
    "state": "Illinois"
  },
  "sn92053240": {
    "title": "Free trader-journal.",
    "earliest_date": "January 02, 1917",
    "raw_date": "1917-01-02",
    "state": "Illinois"
  },
  "sn83045203": {
    "title": "Glas svobode. [volume]",
    "earliest_date": "August 28, 1917",
    "raw_date": "1917-08-28",
    "state": "Illinois"
  },
  "sn79007943": {
    "title": "G\u0142os polek. [volume]",
    "earliest_date": "July 01, 1902",
    "raw_date": "1902-07-01",
    "state": "Illinois"
  },
  "sn82002636": {
    "title": "Hlasatel. [volume]",
    "earliest_date": "January 06, 1920",
    "raw_date": "1920-01-06",
    "state": "Illinois"
  },
  "sn82014968": {
    "title": "The Illinois free trader and LaSalle County commercial advertiser. [volume]",
    "earliest_date": "June 04, 1841",
    "raw_date": "1841-06-04",
    "state": "Illinois"
  },
  "sn92053237": {
    "title": "The Illinois free trader.",
    "earliest_date": "May 23, 1840",
    "raw_date": "1840-05-23",
    "state": "Illinois"
  },
  "sn2008060405": {
    "title": "The Illinois issue.",
    "earliest_date": "January 19, 1906",
    "raw_date": "1906-01-19",
    "state": "Illinois"
  },
  "sn82014079": {
    "title": "Illinois Staats-Zeitung. [volume]",
    "earliest_date": "January 02, 1888",
    "raw_date": "1888-01-02",
    "state": "Illinois"
  },
  "sn85033492": {
    "title": "Illinois Staats-zeitung. [volume]",
    "earliest_date": "March 26, 1863",
    "raw_date": "1863-03-26",
    "state": "Illinois"
  },
  "sn82015060": {
    "title": "The Illinois standard. [volume]",
    "earliest_date": "September 11, 1948",
    "raw_date": "1948-09-11",
    "state": "Illinois"
  },
  "sn88061252": {
    "title": "The Illinois times.",
    "earliest_date": "October 14, 1949",
    "raw_date": "1949-10-14",
    "state": "Illinois"
  },
  "sn94054745": {
    "title": "The Irish republic. [volume]",
    "earliest_date": "May 04, 1867",
    "raw_date": "1867-05-04",
    "state": "Illinois"
  },
  "sn90053038": {
    "title": "The Jewish advance.",
    "earliest_date": "June 14, 1878",
    "raw_date": "1878-06-14",
    "state": "Illinois"
  },
  "sn84024082": {
    "title": "Juliet signal. [volume]",
    "earliest_date": "May 05, 1846",
    "raw_date": "1846-05-05",
    "state": "Illinois"
  },
  "sn00062053": {
    "title": "Katalikas.",
    "earliest_date": "July 14, 1910",
    "raw_date": "1910-07-14",
    "state": "Illinois"
  },
  "sn83045284": {
    "title": "Lietuva. [volume]",
    "earliest_date": "December 05, 1913",
    "raw_date": "1913-12-05",
    "state": "Illinois"
  },
  "sn89080007": {
    "title": "Metropolis weekly gazette.",
    "earliest_date": "July 21, 1911",
    "raw_date": "1911-07-21",
    "state": "Illinois"
  },
  "sn91055359": {
    "title": "Metropolitan news.",
    "earliest_date": "May 07, 1935",
    "raw_date": "1935-05-07",
    "state": "Illinois"
  },
  "sn90054495": {
    "title": "National news.",
    "earliest_date": "October 22, 1915",
    "raw_date": "1915-10-22",
    "state": "Illinois"
  },
  "sn86090451": {
    "title": "The national prohibitionist. [volume]",
    "earliest_date": "December 05, 1907",
    "raw_date": "1907-12-05",
    "state": "Illinois"
  },
  "sn84038582": {
    "title": "The Ottawa free trader. [volume]",
    "earliest_date": "October 06, 1843",
    "raw_date": "1843-10-06",
    "state": "Illinois"
  },
  "sn83035546": {
    "title": "Pokrok. [volume]",
    "earliest_date": "August 15, 1874",
    "raw_date": "1874-08-15",
    "state": "Illinois"
  },
  "sn82014511": {
    "title": "The press and tribune. [volume]",
    "earliest_date": "March 17, 1859",
    "raw_date": "1859-03-17",
    "state": "Illinois"
  },
  "sn83045377": {
    "title": "Proletarec. [volume]",
    "earliest_date": "January 01, 1906",
    "raw_date": "1906-01-01",
    "state": "Illinois"
  },
  "sn82015743": {
    "title": "Rassvet = The dawn. [volume]",
    "earliest_date": "December 01, 1926",
    "raw_date": "1926-12-01",
    "state": "Illinois"
  },
  "sn2008060212": {
    "title": "The Robbins eagle.",
    "earliest_date": "March 03, 1951",
    "raw_date": "1951-03-03",
    "state": "Illinois"
  },
  "sn92053933": {
    "title": "The Rock Island Argus and daily union.",
    "earliest_date": "March 25, 1920",
    "raw_date": "1920-03-25",
    "state": "Illinois"
  },
  "sn92053934": {
    "title": "Rock Island Argus.",
    "earliest_date": "December 02, 1893",
    "raw_date": "1893-12-02",
    "state": "Illinois"
  },
  "sn92053941": {
    "title": "Rock Island Argus.",
    "earliest_date": "June 19, 1871",
    "raw_date": "1871-06-19",
    "state": "Illinois"
  },
  "sn92053943": {
    "title": "The Rock Island Argus.",
    "earliest_date": "March 05, 1877",
    "raw_date": "1877-03-05",
    "state": "Illinois"
  },
  "sn85034301": {
    "title": "The Rock Island daily Argus. [volume]",
    "earliest_date": "November 29, 1872",
    "raw_date": "1872-11-29",
    "state": "Illinois"
  },
  "sn92053945": {
    "title": "Rock Island daily Argus.",
    "earliest_date": "October 04, 1886",
    "raw_date": "1886-10-04",
    "state": "Illinois"
  },
  "sn82014400": {
    "title": "Russkii\u0306 vestnik = Russian daily herald. [volume]",
    "earliest_date": "May 01, 1926",
    "raw_date": "1926-05-01",
    "state": "Illinois"
  },
  "sn82015744": {
    "title": "Russkii\u0306 vestnik i rassvet = Russian daily herald and dawn. [volume]",
    "earliest_date": "May 15, 1926",
    "raw_date": "1926-05-15",
    "state": "Illinois"
  },
  "sn84025827": {
    "title": "The state capital. [volume]",
    "earliest_date": "March 28, 1891",
    "raw_date": "1891-03-28",
    "state": "Illinois"
  },
  "sn90054490": {
    "title": "Strike bulletin.",
    "earliest_date": "April 09, 1913",
    "raw_date": "1913-04-09",
    "state": "Illinois"
  },
  "sn82015409": {
    "title": "Sunday Chicago bee. [volume]",
    "earliest_date": "May 01, 1938",
    "raw_date": "1938-05-01",
    "state": "Illinois"
  },
  "sn82014268": {
    "title": "Svobodnai\ufe20a\ufe21 Rossii\ufe20a\ufe21 = Free Russia. [volume]",
    "earliest_date": "July 06, 1918",
    "raw_date": "1918-07-06",
    "state": "Illinois"
  },
  "sn00062200": {
    "title": "Telegraf.",
    "earliest_date": "May 31, 1892",
    "raw_date": "1892-05-31",
    "state": "Illinois"
  },
  "sn94054571": {
    "title": "The theocrat. [volume]",
    "earliest_date": "February 21, 1914",
    "raw_date": "1914-02-21",
    "state": "Illinois"
  },
  "sn96071000": {
    "title": "Twin city review. [volume]",
    "earliest_date": "November 19, 1920",
    "raw_date": "1920-11-19",
    "state": "Illinois"
  },
  "sn98021761": {
    "title": "Ty\u0301denni\u0301 hlasatel.",
    "earliest_date": "July 20, 1892",
    "raw_date": "1892-07-20",
    "state": "Illinois"
  },
  "sn90053049": {
    "title": "The Universalist. [volume]",
    "earliest_date": "July 03, 1886",
    "raw_date": "1886-07-03",
    "state": "Illinois"
  },
  "sn82015332": {
    "title": "Vandalia Whig and Illinois intelligencer. [volume]",
    "earliest_date": "March 28, 1832",
    "raw_date": "1832-03-28",
    "state": "Illinois"
  },
  "sn83045868": {
    "title": "Vorbote. [volume]",
    "earliest_date": "October 10, 1917",
    "raw_date": "1917-10-10",
    "state": "Illinois"
  },
  "sn83016811": {
    "title": "Western appeal. [volume]",
    "earliest_date": "June 13, 1885",
    "raw_date": "1885-06-13",
    "state": "Illinois"
  },
  "sn89077510": {
    "title": "The workingman&#39;s advocate. [volume]",
    "earliest_date": "September 17, 1864",
    "raw_date": "1864-09-17",
    "state": "Illinois"
  },
  "2017218620": {
    "title": "Zgoda : Wydania dla niewiast. [volume]",
    "earliest_date": "September 13, 1900",
    "raw_date": "1900-09-13",
    "state": "Illinois"
  },
  "2017218621": {
    "title": "Zgoda : Wydanie dla me\u0328z\u0307czyzn. [volume]",
    "earliest_date": "January 02, 1902",
    "raw_date": "1902-01-02",
    "state": "Illinois"
  },
  "2017218622": {
    "title": "Zgoda = Unity. [volume]",
    "earliest_date": "January 01, 1914",
    "raw_date": "1914-01-01",
    "state": "Illinois"
  },
  "sn91037345": {
    "title": "Zgoda = Unity. [volume]",
    "earliest_date": "January 04, 1893",
    "raw_date": "1893-01-04",
    "state": "Illinois"
  },
  "sn86071520": {
    "title": "The Alexandria gazette. [volume]",
    "earliest_date": "April 02, 1822",
    "raw_date": "1822-04-02",
    "state": "District of Columbia"
  },
  "sn85025007": {
    "title": "Alexandria gazette. [volume]",
    "earliest_date": "January 01, 1834",
    "raw_date": "1834-01-01",
    "state": "District of Columbia"
  },
  "sn82014594": {
    "title": "American telegraph. [volume]",
    "earliest_date": "March 24, 1851",
    "raw_date": "1851-03-24",
    "state": "District of Columbia"
  },
  "sn82014015": {
    "title": "The American. [volume]",
    "earliest_date": "July 31, 1857",
    "raw_date": "1857-07-31",
    "state": "District of Columbia"
  },
  "sn84025890": {
    "title": "The bee. [volume]",
    "earliest_date": "June 10, 1882",
    "raw_date": "1882-06-10",
    "state": "District of Columbia"
  },
  "sn83027091": {
    "title": "The colored American. [volume]",
    "earliest_date": "August 11, 1894",
    "raw_date": "1894-08-11",
    "state": "District of Columbia"
  },
  "sn82014761": {
    "title": "Columbia. [volume]",
    "earliest_date": "October 17, 1863",
    "raw_date": "1863-10-17",
    "state": "District of Columbia"
  },
  "sn82014769": {
    "title": "The Columbian fountain. [volume]",
    "earliest_date": "November 04, 1845",
    "raw_date": "1845-11-04",
    "state": "District of Columbia"
  },
  "sn87062228": {
    "title": "The Critic and record.",
    "earliest_date": "March 26, 1891",
    "raw_date": "1891-03-26",
    "state": "District of Columbia"
  },
  "sn2008058171": {
    "title": "The critic.",
    "earliest_date": "December 13, 1890",
    "raw_date": "1890-12-13",
    "state": "District of Columbia"
  },
  "2012271201": {
    "title": "Cronaca sovversiva. [volume]",
    "earliest_date": "June 06, 1903",
    "raw_date": "1903-06-06",
    "state": "District of Columbia"
  },
  "sn85042002": {
    "title": "Daily American organ. [volume]",
    "earliest_date": "November 13, 1854",
    "raw_date": "1854-11-13",
    "state": "District of Columbia"
  },
  "sn82014593": {
    "title": "Daily American telegraph. [volume]",
    "earliest_date": "December 22, 1851",
    "raw_date": "1851-12-22",
    "state": "District of Columbia"
  },
  "sn82014402": {
    "title": "Daily critic. [volume]",
    "earliest_date": "May 22, 1880",
    "raw_date": "1880-05-22",
    "state": "District of Columbia"
  },
  "sn2008058170": {
    "title": "The daily critic.",
    "earliest_date": "May 26, 1890",
    "raw_date": "1890-05-26",
    "state": "District of Columbia"
  },
  "sn83045461": {
    "title": "Daily evening star. [volume]",
    "earliest_date": "December 16, 1852",
    "raw_date": "1852-12-16",
    "state": "District of Columbia"
  },
  "sn84020074": {
    "title": "The daily Madisonian. [volume]",
    "earliest_date": "December 15, 1841",
    "raw_date": "1841-12-15",
    "state": "District of Columbia"
  },
  "sn86053546": {
    "title": "Daily national era. [volume]",
    "earliest_date": "January 02, 1854",
    "raw_date": "1854-01-02",
    "state": "District of Columbia"
  },
  "sn86053572": {
    "title": "Daily national Republican.",
    "earliest_date": "January 14, 1870",
    "raw_date": "1870-01-14",
    "state": "District of Columbia"
  },
  "sn86053570": {
    "title": "Daily national Republican. [volume]",
    "earliest_date": "November 10, 1862",
    "raw_date": "1862-11-10",
    "state": "District of Columbia"
  },
  "sn82014405": {
    "title": "The daily national Whig. [volume]",
    "earliest_date": "August 09, 1847",
    "raw_date": "1847-08-09",
    "state": "District of Columbia"
  },
  "sn82014166": {
    "title": "The daily republic. [volume]",
    "earliest_date": "July 06, 1853",
    "raw_date": "1853-07-06",
    "state": "District of Columbia"
  },
  "sn82003410": {
    "title": "The daily union. [volume]",
    "earliest_date": "May 01, 1845",
    "raw_date": "1845-05-01",
    "state": "District of Columbia"
  },
  "sn82014424": {
    "title": "The Evening critic. [volume]",
    "earliest_date": "June 13, 1881",
    "raw_date": "1881-06-13",
    "state": "District of Columbia"
  },
  "sn82000195": {
    "title": "The Evening post. [volume]",
    "earliest_date": "October 15, 1888",
    "raw_date": "1888-10-15",
    "state": "District of Columbia"
  },
  "sn83045462": {
    "title": "Evening star. [volume]",
    "earliest_date": "October 09, 1854",
    "raw_date": "1854-10-09",
    "state": "District of Columbia"
  },
  "sn84024441": {
    "title": "The evening times. [volume]",
    "earliest_date": "August 05, 1895",
    "raw_date": "1895-08-05",
    "state": "District of Columbia"
  },
  "sn82014159": {
    "title": "The hatchet. [volume]",
    "earliest_date": "April 29, 1900",
    "raw_date": "1900-04-29",
    "state": "District of Columbia"
  },
  "sn84025835": {
    "title": "The leader. [volume]",
    "earliest_date": "October 12, 1889",
    "raw_date": "1889-10-12",
    "state": "District of Columbia"
  },
  "sn82014039": {
    "title": "The Madisonian. [volume]",
    "earliest_date": "February 02, 1839",
    "raw_date": "1839-02-02",
    "state": "District of Columbia"
  },
  "sn82015015": {
    "title": "The Madisonian. [volume]",
    "earliest_date": "August 16, 1837",
    "raw_date": "1837-08-16",
    "state": "District of Columbia"
  },
  "sn84024442": {
    "title": "The morning times. [volume]",
    "earliest_date": "July 04, 1895",
    "raw_date": "1895-07-04",
    "state": "District of Columbia"
  },
  "sn84026752": {
    "title": "The national era. [volume]",
    "earliest_date": "January 03, 1850",
    "raw_date": "1850-01-03",
    "state": "District of Columbia"
  },
  "sn82015056": {
    "title": "The national forum. [volume]",
    "earliest_date": "May 28, 1910",
    "raw_date": "1910-05-28",
    "state": "District of Columbia"
  },
  "sn83045242": {
    "title": "The national intelligencer and Washington advertiser. [volume]",
    "earliest_date": "October 31, 1800",
    "raw_date": "1800-10-31",
    "state": "District of Columbia"
  },
  "sn84025834": {
    "title": "The national leader. [volume]",
    "earliest_date": "December 08, 1888",
    "raw_date": "1888-12-08",
    "state": "District of Columbia"
  },
  "sn82015130": {
    "title": "The National Republican. [volume]",
    "earliest_date": "November 17, 1885",
    "raw_date": "1885-11-17",
    "state": "District of Columbia"
  },
  "sn86053573": {
    "title": "National Republican.",
    "earliest_date": "November 26, 1872",
    "raw_date": "1872-11-26",
    "state": "District of Columbia"
  },
  "sn86053571": {
    "title": "The national Republican. [volume]",
    "earliest_date": "April 02, 1866",
    "raw_date": "1866-04-02",
    "state": "District of Columbia"
  },
  "sn82014760": {
    "title": "The national Republican. [volume]",
    "earliest_date": "November 26, 1860",
    "raw_date": "1860-11-26",
    "state": "District of Columbia"
  },
  "sn96027351": {
    "title": "National savings bank. [online resource]",
    "earliest_date": "January 01, 1868",
    "raw_date": "1868-01-01",
    "state": "District of Columbia"
  },
  "sn82016187": {
    "title": "The National tribune. [volume]",
    "earliest_date": "October 01, 1877",
    "raw_date": "1877-10-01",
    "state": "District of Columbia"
  },
  "sn82003399": {
    "title": "The national whig. [volume]",
    "earliest_date": "April 07, 1847",
    "raw_date": "1847-04-07",
    "state": "District of Columbia"
  },
  "sn86053569": {
    "title": "The native American. [volume]",
    "earliest_date": "August 10, 1837",
    "raw_date": "1837-08-10",
    "state": "District of Columbia"
  },
  "sn84024437": {
    "title": "New era. [volume]",
    "earliest_date": "January 13, 1870",
    "raw_date": "1870-01-13",
    "state": "District of Columbia"
  },
  "sn84026753": {
    "title": "New national era. [volume]",
    "earliest_date": "September 08, 1870",
    "raw_date": "1870-09-08",
    "state": "District of Columbia"
  },
  "sn82014434": {
    "title": "The republic. [volume]",
    "earliest_date": "June 13, 1849",
    "raw_date": "1849-06-13",
    "state": "District of Columbia"
  },
  "sn82014763": {
    "title": "The southern press. [volume]",
    "earliest_date": "June 25, 1850",
    "raw_date": "1850-06-25",
    "state": "District of Columbia"
  },
  "sn82014764": {
    "title": "The southern press. [volume]",
    "earliest_date": "June 18, 1850",
    "raw_date": "1850-06-18",
    "state": "District of Columbia"
  },
  "sn82016357": {
    "title": "The suburban citizen.",
    "earliest_date": "January 06, 1900",
    "raw_date": "1900-01-06",
    "state": "District of Columbia"
  },
  "sn82016351": {
    "title": "The Sunday globe. [volume]",
    "earliest_date": "May 05, 1901",
    "raw_date": "1901-05-05",
    "state": "District of Columbia"
  },
  "sn82016373": {
    "title": "The Sunday herald and weekly national intelligencer. [volume]",
    "earliest_date": "February 06, 1887",
    "raw_date": "1887-02-06",
    "state": "District of Columbia"
  },
  "sn85042682": {
    "title": "The Sunday herald. [volume]",
    "earliest_date": "September 14, 1879",
    "raw_date": "1879-09-14",
    "state": "District of Columbia"
  },
  "sn82016352": {
    "title": "Sunday morning globe. [volume]",
    "earliest_date": "August 18, 1901",
    "raw_date": "1901-08-18",
    "state": "District of Columbia"
  },
  "sn82016353": {
    "title": "Sunday Washington globe. [volume]",
    "earliest_date": "December 22, 1901",
    "raw_date": "1901-12-22",
    "state": "District of Columbia"
  },
  "sn82014333": {
    "title": "Ta\u0308glicher Washingtoner Anzeiger. [volume]",
    "earliest_date": "January 01, 1873",
    "raw_date": "1873-01-01",
    "state": "District of Columbia"
  },
  "sn85054468": {
    "title": "The times. [volume]",
    "earliest_date": "March 12, 1897",
    "raw_date": "1897-03-12",
    "state": "District of Columbia"
  },
  "sn84025891": {
    "title": "The Washington bee. [volume]",
    "earliest_date": "May 29, 1886",
    "raw_date": "1886-05-29",
    "state": "District of Columbia"
  },
  "sn82000205": {
    "title": "The Washington critic. [volume]",
    "earliest_date": "May 07, 1885",
    "raw_date": "1885-05-07",
    "state": "District of Columbia"
  },
  "sn2008058169": {
    "title": "The Washington critic.",
    "earliest_date": "January 27, 1890",
    "raw_date": "1890-01-27",
    "state": "District of Columbia"
  },
  "sn82000189": {
    "title": "The Washington critic. [volume]",
    "earliest_date": "January 07, 1889",
    "raw_date": "1889-01-07",
    "state": "District of Columbia"
  },
  "sn83045433": {
    "title": "The Washington herald. [volume]",
    "earliest_date": "October 08, 1906",
    "raw_date": "1906-10-08",
    "state": "District of Columbia"
  },
  "sn82014726": {
    "title": "Washington Journal. [volume]",
    "earliest_date": "April 07, 1888",
    "raw_date": "1888-04-07",
    "state": "District of Columbia"
  },
  "sn84020104": {
    "title": "Washington sentinel. [volume]",
    "earliest_date": "September 24, 1853",
    "raw_date": "1853-09-24",
    "state": "District of Columbia"
  },
  "sn82014835": {
    "title": "Washington sentinel. [volume]",
    "earliest_date": "March 27, 1855",
    "raw_date": "1855-03-27",
    "state": "District of Columbia"
  },
  "sn82016354": {
    "title": "Washington sentinel. [volume]",
    "earliest_date": "January 01, 1898",
    "raw_date": "1898-01-01",
    "state": "District of Columbia"
  },
  "sn84026749": {
    "title": "The Washington times. [volume]",
    "earliest_date": "December 01, 1902",
    "raw_date": "1902-12-01",
    "state": "District of Columbia"
  },
  "sn87062244": {
    "title": "The Washington times.",
    "earliest_date": "March 18, 1894",
    "raw_date": "1894-03-18",
    "state": "District of Columbia"
  },
  "sn87062245": {
    "title": "The Washington times.",
    "earliest_date": "June 30, 1901",
    "raw_date": "1901-06-30",
    "state": "District of Columbia"
  },
  "sn87062236": {
    "title": "The Washington tribune. [volume]",
    "earliest_date": "January 05, 1924",
    "raw_date": "1924-01-05",
    "state": "District of Columbia"
  },
  "sn82006534": {
    "title": "The Washington union. [volume]",
    "earliest_date": "April 16, 1857",
    "raw_date": "1857-04-16",
    "state": "District of Columbia"
  },
  "sn87062234": {
    "title": "The Washington weekly post.",
    "earliest_date": "February 07, 1899",
    "raw_date": "1899-02-07",
    "state": "District of Columbia"
  },
  "sn82015822": {
    "title": "Washingtoner Intelligenzblatt. [volume]",
    "earliest_date": "April 02, 1859",
    "raw_date": "1859-04-02",
    "state": "District of Columbia"
  },
  "sn84026744": {
    "title": "Washingtoner journal. [volume]",
    "earliest_date": "March 31, 1873",
    "raw_date": "1873-03-31",
    "state": "District of Columbia"
  },
  "sn82016312": {
    "title": "The Washingtonian. [volume]",
    "earliest_date": "June 07, 1845",
    "raw_date": "1845-06-07",
    "state": "District of Columbia"
  },
  "sn82014016": {
    "title": "Weekly American. [volume]",
    "earliest_date": "January 09, 1858",
    "raw_date": "1858-01-09",
    "state": "District of Columbia"
  },
  "sn83045784": {
    "title": "Weekly national intelligencer. [volume]",
    "earliest_date": "July 01, 1843",
    "raw_date": "1843-07-01",
    "state": "District of Columbia"
  },
  "sn82016441": {
    "title": "The weekly news. [volume]",
    "earliest_date": "August 07, 1909",
    "raw_date": "1909-08-07",
    "state": "District of Columbia"
  },
  "sn82016317": {
    "title": "The Whig standard. [volume]",
    "earliest_date": "November 06, 1843",
    "raw_date": "1843-11-06",
    "state": "District of Columbia"
  }
}